word_mcp/__init__.py
word_mcp/__main__.py
word_mcp/server.py
word_mcp/server_windows.py
word_mcp/word_mcp_server_windows.py
word_mcp/backends/__init__.py
word_mcp/backends/base.py
word_mcp/backends/factory.py
word_mcp/backends/macos.py
word_mcp-1.0.3.dist-info/licenses/LICENSE
word_mcp-1.0.3.dist-info/METADATA
word_mcp-1.0.3.dist-info/WHEEL
word_mcp-1.0.3.dist-info/entry_points.txt
word_mcp-1.0.3.dist-info/top_level.txt
word_mcp-1.0.3.dist-info/RECORD
