Metadata-Version: 2.4
Name: word-mcp
Version: 1.0.3
Summary: A Model Context Protocol server for Microsoft Word integration
Author-email: Jie Tong <tongjie@gmail.com>
License-Expression: MIT
Project-URL: Homepage, https://github.com/word-mcp/word-mcp
Project-URL: Documentation, https://github.com/word-mcp/word-mcp#readme
Project-URL: Repository, https://github.com/word-mcp/word-mcp.git
Project-URL: Bug Tracker, https://github.com/word-mcp/word-mcp/issues
Keywords: mcp,word,microsoft,automation,ai,llm
Classifier: Development Status :: 4 - Beta
Classifier: Intended Audience :: Developers
Classifier: Operating System :: OS Independent
Classifier: Programming Language :: Python :: 3
Classifier: Programming Language :: Python :: 3.8
Classifier: Programming Language :: Python :: 3.9
Classifier: Programming Language :: Python :: 3.10
Classifier: Programming Language :: Python :: 3.11
Classifier: Programming Language :: Python :: 3.12
Classifier: Topic :: Software Development :: Libraries :: Python Modules
Classifier: Topic :: Text Processing :: General
Classifier: Topic :: Office/Business :: Office Suites
Requires-Python: >=3.8
License-File: LICENSE
Requires-Dist: mcp>=1.0.0
Requires-Dist: pydantic>=2.0.0
Requires-Dist: asyncio-throttle>=1.0.0
Requires-Dist: pywin32>=306; platform_system == "Windows"
Provides-Extra: dev
Requires-Dist: pytest>=7.0.0; extra == "dev"
Requires-Dist: pytest-asyncio>=0.21.0; extra == "dev"
Requires-Dist: black>=22.0.0; extra == "dev"
Requires-Dist: isort>=5.0.0; extra == "dev"
Requires-Dist: mypy>=1.0.0; extra == "dev"
Requires-Dist: pre-commit>=2.0.0; extra == "dev"
Dynamic: license-file
